j2cli/__init__.py
j2cli/cli.py
j2cli/context.py
j2cli/extras/__init__.py
j2cli/extras/customize.py
j2cli/extras/filters.py
j2_cmd-0.0.1.dist-info/LICENSE
j2_cmd-0.0.1.dist-info/METADATA
j2_cmd-0.0.1.dist-info/WHEEL
j2_cmd-0.0.1.dist-info/entry_points.txt
j2_cmd-0.0.1.dist-info/top_level.txt
j2_cmd-0.0.1.dist-info/RECORD
